modax/__about__.py
modax/__init__.py
modax-0.0.1.dist-info/METADATA
modax-0.0.1.dist-info/WHEEL
modax-0.0.1.dist-info/licenses/LICENSE
modax-0.0.1.dist-info/RECORD
