Metadata-Version: 2.3
Name: modax
Version: 0.0.1
Summary: Modax: A modular JAX-based library to accelerate AI research
Project-URL: Documentation, https://github.com/leandrolcampos/modax#readme
Project-URL: Issues, https://github.com/leandrolcampos/modax/issues
Project-URL: Source, https://github.com/leandrolcampos/modax
Author: Leandro Lacerda Campos, The Modax Authors
License:                                  Apache License
License-File: LICENSE
Classifier: Development Status :: 4 - Beta
Classifier: Programming Language :: Python
Classifier: Programming Language :: Python :: 3.10
Classifier: Programming Language :: Python :: 3.11
Classifier: Programming Language :: Python :: 3.12
Classifier: Programming Language :: Python :: Implementation :: CPython
Classifier: Programming Language :: Python :: Implementation :: PyPy
Requires-Python: >=3.10
